pypreg/__init__.py
pypreg/adverse_pregnancy_outcomes/__init__.py
pypreg/adverse_pregnancy_outcomes/adverse_pregnancy_outcomes.py
pypreg/adverse_pregnancy_outcomes/cesarean_mapping.py
pypreg/adverse_pregnancy_outcomes/fetal_growth_mapping.py
pypreg/adverse_pregnancy_outcomes/gestational_dm_mapping.py
pypreg/adverse_pregnancy_outcomes/gestational_ht_mapping.py
pypreg/adverse_pregnancy_outcomes/preeclampsia_mapping.py
pypreg/obstetric_comorbidity/__init__.py
pypreg/obstetric_comorbidity/attach_map.py
pypreg/obstetric_comorbidity/bateman_mapping.py
pypreg/obstetric_comorbidity/leonard_mapping.py
pypreg/obstetric_comorbidity/obstetric_index.py
pypreg/obstetric_comorbidity/score.py
pypreg/pregnancy_outcome/__init__.py
pypreg/pregnancy_outcome/attach_map.py
pypreg/pregnancy_outcome/outcome_map.py
pypreg/pregnancy_outcome/process_outcome.py
pypreg/smm/__init__.py
pypreg/smm/smm.py
pypreg/smm/smm_mapping.py
pypreg-0.1.0.dist-info/METADATA
pypreg-0.1.0.dist-info/WHEEL
pypreg-0.1.0.dist-info/licenses/LICENSE
pypreg-0.1.0.dist-info/RECORD
