Metadata-Version: 2.3
Name: pypreg
Version: 0.1.0
Summary: A collection of tools to assist with pregnancy research.
Project-URL: Homepage, https://github.com/dpwh24/pypreg
Project-URL: Issues, https://github.com/dpwh24/pypreg/issues
Author-email: David Walsh <dwalsh@umkc.edu>
License:                     GNU GENERAL PUBLIC LICENSE
License-File: LICENSE
Classifier: Development Status :: 4 - Beta
Classifier: Intended Audience :: Healthcare Industry
Classifier: Intended Audience :: Science/Research
Classifier: License :: OSI Approved :: GNU General Public License v3 (GPLv3)
Classifier: Operating System :: OS Independent
Classifier: Programming Language :: Python :: 3
Classifier: Topic :: Scientific/Engineering :: Bio-Informatics
Requires-Python: >=3.10
Requires-Dist: pandas~=2.2.2
